[
  {
    "Koşu": "1",
    "At İsmi": "PENÇSİR",
    "Profil Linki": "/at/102038/pencsir",
    "Jokey": "K.Tokaçoğlu",
    "Son Kilo": "58.5",
    "Son Mesafe": "1400",
    "Son Pist": "Çim",
    "Son Derece": "1.33.44",
    "Kilo": "57",
    "Bugünkü Mesafe": "1600",
    "Bugünkü Pist": "Çim",
    "Şehir": "İstanbul",
    "Son Hipodrom": "Bursa"
  },
  {
    "Koşu": "1",
    "At İsmi": "KARA AYHAN",
    "Profil Linki": "/at/101527/kara-ayhan",
    "Jokey": "Murat Keçeci",
    "Son Kilo": "53.5",
    "Son Mesafe": "1200",
    "Son Pist": "Kum",
    "Son Derece": "1.30.24",
    "Kilo": "57.2",
    "Bugünkü Mesafe": "1600",
    "Bugünkü Pist": "Çim",
    "Şehir": "İstanbul",
    "Son Hipodrom": "Ankara"
  },
  {
    "Koşu": "1",
    "At İsmi": "LOSTRA",
    "Profil Linki": "/at/101214/lostra",
    "Jokey": "Ahmet Çelik",
    "Son Kilo": "55.5",
    "Son Mesafe": "1400",
    "Son Pist": "Çim",
    "Son Derece": "1.33.82",
    "Kilo": "57",
    "Bugünkü Mesafe": "1600",
    "Bugünkü Pist": "Çim",
    "Şehir": "İstanbul",
    "Son Hipodrom": "İstanbul"
  },
  {
    "Koşu": "1",
    "At İsmi": "SERPENÇE",
    "Profil Linki": "/at/102075/serpence",
    "Jokey": "E.Çankaya",
    "Son Kilo": "54.5",
    "Son Mesafe": "1500",
    "Son Pist": "Sentetik",
    "Son Derece": "1.47.15",
    "Kilo": "60",
    "Bugünkü Mesafe": "1600",
    "Bugünkü Pist": "Çim",
    "Şehir": "İstanbul",
    "Son Hipodrom": "İstanbul"
  },
  {
    "Koşu": "1",
    "At İsmi": "ALMUTANABİY",
    "Profil Linki": "/at/102339/almutanabiy",
    "Jokey": "V.Abiş",
    "Son Kilo": "53.5",
    "Son Mesafe": "1400",
    "Son Pist": "Çim",
    "Son Derece": "1.34.45",
    "Kilo": "57.2",
    "Bugünkü Mesafe": "1600",
    "Bugünkü Pist": "Çim",
    "Şehir": "İstanbul",
    "Son Hipodrom": "İstanbul"
  },
  {
    "Koşu": "1",
    "At İsmi": "CEVATHAN",
    "Profil Linki": "/at/103004/cevathan",
    "Jokey": "B.Çığla",
    "Son Kilo": "50",
    "Son Mesafe": "1200",
    "Son Pist": "Çim",
    "Son Derece": "1.20.62",
    "Kilo": "60",
    "Bugünkü Mesafe": "1600",
    "Bugünkü Pist": "Çim",
    "Şehir": "İstanbul",
    "Son Hipodrom": "Bursa"
  },
  {
    "Koşu": "1",
    "At İsmi": "BEROSH",
    "Profil Linki": "/at/101486/berosh",
    "Jokey": "Hakan Yıldız",
    "Son Kilo": "50.5",
    "Son Mesafe": "1400",
    "Son Pist": "Çim",
    "Son Derece": "1.41.23",
    "Kilo": "59",
    "Bugünkü Mesafe": "1600",
    "Bugünkü Pist": "Çim",
    "Şehir": "İstanbul",
    "Son Hipodrom": "İstanbul"
  },
  {
    "Koşu": "1",
    "At İsmi": "TATARUŞAĞI",
    "Profil Linki": "/at/101591/tatarusagi",
    "Jokey": "Z.Karabulut",
    "Son Kilo": "50",
    "Son Mesafe": "1400",
    "Son Pist": "Kum",
    "Son Derece": "1.39.91",
    "Kilo": "55.3",
    "Bugünkü Mesafe": "1600",
    "Bugünkü Pist": "Çim",
    "Şehir": "İstanbul",
    "Son Hipodrom": "Bursa"
  },
  {
    "Koşu": "2",
    "At İsmi": "ERULİNA",
    "Profil Linki": "/at/103779/erulina",
    "Jokey": "M.Kaya",
    "Son Kilo": "60",
    "Son Mesafe": "1400",
    "Son Pist": "Kum",
    "Son Derece": "1.32.42",
    "Kilo": "59",
    "Bugünkü Mesafe": "1300",
    "Bugünkü Pist": "Sentetik",
    "Şehir": "İstanbul",
    "Son Hipodrom": "Bursa"
  },
  {
    "Koşu": "2",
    "At İsmi": "AGILE GIRL",
    "Profil Linki": "/at/103879/agile-girl",
    "Jokey": "S.Tırpan",
    "Son Kilo": "57",
    "Son Mesafe": "1200",
    "Son Pist": "Çim",
    "Son Derece": "1.12.17",
    "Kilo": "57",
    "Bugünkü Mesafe": "1300",
    "Bugünkü Pist": "Sentetik",
    "Şehir": "İstanbul",
    "Son Hipodrom": "Bursa"
  },
  {
    "Koşu": "2",
    "At İsmi": "BONNIE PARKER",
    "Profil Linki": "/at/104619/bonnie-parker",
    "Jokey": "Murat Keçeci",
    "Son Kilo": "54",
    "Son Mesafe": "1400",
    "Son Pist": "Kum",
    "Son Derece": "1.35.56",
    "Kilo": "57",
    "Bugünkü Mesafe": "1300",
    "Bugünkü Pist": "Sentetik",
    "Şehir": "İstanbul",
    "Son Hipodrom": "Kocaeli"
  },
  {
    "Koşu": "2",
    "At İsmi": "CROWN JEWEL",
    "Profil Linki": "/at/102456/crown-jewel",
    "Jokey": "G.Özçelik",
    "Son Kilo": "57",
    "Son Mesafe": "1200",
    "Son Pist": "Sentetik",
    "Son Derece": "1.15.16",
    "Kilo": "55.8",
    "Bugünkü Mesafe": "1300",
    "Bugünkü Pist": "Sentetik",
    "Şehir": "İstanbul",
    "Son Hipodrom": "İstanbul"
  },
  {
    "Koşu": "2",
    "At İsmi": "DAELLA",
    "Profil Linki": "/at/102665/daella",
    "Jokey": "A.Yıldız",
    "Son Kilo": "57",
    "Son Mesafe": "1300",
    "Son Pist": "Çim",
    "Son Derece": "1.21.99",
    "Kilo": "57",
    "Bugünkü Mesafe": "1300",
    "Bugünkü Pist": "Sentetik",
    "Şehir": "İstanbul",
    "Son Hipodrom": "İstanbul"
  },
  {
    "Koşu": "2",
    "At İsmi": "DREAM OF UYGUR",
    "Profil Linki": "/at/103573/dream-of-uygur",
    "Jokey": "B.Akçay",
    "Son Kilo": "57",
    "Son Mesafe": "1200",
    "Son Pist": "Sentetik",
    "Son Derece": "1.17.39",
    "Kilo": "55.8",
    "Bugünkü Mesafe": "1300",
    "Bugünkü Pist": "Sentetik",
    "Şehir": "İstanbul",
    "Son Hipodrom": "İstanbul"
  },
  {
    "Koşu": "2",
    "At İsmi": "HIGH HILLS",
    "Profil Linki": "/at/104012/high-hills",
    "Jokey": "V.Abiş",
    "Son Kilo": "57",
    "Son Mesafe": "1200",
    "Son Pist": "Kum",
    "Son Derece": "1.17.17",
    "Kilo": "55",
    "Bugünkü Mesafe": "1300",
    "Bugünkü Pist": "Sentetik",
    "Şehir": "İstanbul",
    "Son Hipodrom": "Ankara"
  },
  {
    "Koşu": "2",
    "At İsmi": "İSMERİA",
    "Profil Linki": "/at/103122/ismeria",
    "Jokey": "Ö.Yıldırım",
    "Son Kilo": "57",
    "Son Mesafe": "1300",
    "Son Pist": "Çim",
    "Son Derece": "1.19.34",
    "Kilo": "57",
    "Bugünkü Mesafe": "1300",
    "Bugünkü Pist": "Sentetik",
    "Şehir": "İstanbul",
    "Son Hipodrom": "İstanbul"
  },
  {
    "Koşu": "2",
    "At İsmi": "JAEHAERA",
    "Profil Linki": "/at/102669/jaehaera",
    "Jokey": "G.Kocakaya",
    "Son Kilo": "57",
    "Son Mesafe": "1400",
    "Son Pist": "Çim",
    "Son Derece": "1.25.79",
    "Kilo": "57",
    "Bugünkü Mesafe": "1300",
    "Bugünkü Pist": "Sentetik",
    "Şehir": "İstanbul",
    "Son Hipodrom": "İstanbul"
  },
  {
    "Koşu": "2",
    "At İsmi": "MISS STRONG",
    "Profil Linki": "/at/103128/miss-strong",
    "Jokey": "Y.Gökçe",
    "Son Kilo": "53",
    "Son Mesafe": "1200",
    "Son Pist": "Sentetik",
    "Son Derece": "1.16.10",
    "Kilo": "55",
    "Bugünkü Mesafe": "1300",
    "Bugünkü Pist": "Sentetik",
    "Şehir": "İstanbul",
    "Son Hipodrom": "İstanbul"
  },
  {
    "Koşu": "2",
    "At İsmi": "NINETEEN",
    "Profil Linki": "/at/104335/nineteen",
    "Jokey": "E.Aktuğ",
    "Son Kilo": "57",
    "Son Mesafe": "1200",
    "Son Pist": "Sentetik",
    "Son Derece": "1.15.56",
    "Kilo": "57",
    "Bugünkü Mesafe": "1300",
    "Bugünkü Pist": "Sentetik",
    "Şehir": "İstanbul",
    "Son Hipodrom": "İstanbul"
  },
  {
    "Koşu": "3",
    "At İsmi": "KUNYA",
    "Profil Linki": "/at/94699/kunya",
    "Jokey": "C.Paso",
    "Son Kilo": "63",
    "Son Mesafe": "1400",
    "Son Pist": "Çim",
    "Son Derece": "1.34.17",
    "Kilo": "62",
    "Bugünkü Mesafe": "1600",
    "Bugünkü Pist": "Çim",
    "Şehir": "İstanbul",
    "Son Hipodrom": "İstanbul"
  },
  {
    "Koşu": "3",
    "At İsmi": "GÜROBASI",
    "Profil Linki": "/at/88882/gurobasi",
    "Jokey": "A.E.Elmas",
    "Son Kilo": "59.5",
    "Son Mesafe": "1400",
    "Son Pist": "Kum",
    "Son Derece": "1.37.68",
    "Kilo": "62.5",
    "Bugünkü Mesafe": "1600",
    "Bugünkü Pist": "Çim",
    "Şehir": "İstanbul",
    "Son Hipodrom": "Kocaeli"
  },
  {
    "Koşu": "3",
    "At İsmi": "DEKÇİ BEY",
    "Profil Linki": "/at/98003/dekci-bey",
    "Jokey": "G.Kocakaya",
    "Son Kilo": "57.5",
    "Son Mesafe": "1700",
    "Son Pist": "Çim",
    "Son Derece": "1.56.20",
    "Kilo": "58.2",
    "Bugünkü Mesafe": "1600",
    "Bugünkü Pist": "Çim",
    "Şehir": "İstanbul",
    "Son Hipodrom": "İzmir"
  },
  {
    "Koşu": "3",
    "At İsmi": "TAŞUCU",
    "Profil Linki": "/at/93617/tasucu",
    "Jokey": "Ahmet Çelik",
    "Son Kilo": "58.5",
    "Son Mesafe": "2200",
    "Son Pist": "Çim",
    "Son Derece": "2.35.58",
    "Kilo": "60",
    "Bugünkü Mesafe": "1600",
    "Bugünkü Pist": "Çim",
    "Şehir": "İstanbul",
    "Son Hipodrom": "İstanbul"
  },
  {
    "Koşu": "3",
    "At İsmi": "KULAGER",
    "Profil Linki": "/at/98077/kulager",
    "Jokey": "Müs.Çelik",
    "Son Kilo": "56.5",
    "Son Mesafe": "1300",
    "Son Pist": "Sentetik",
    "Son Derece": "1.26.34",
    "Kilo": "52",
    "Bugünkü Mesafe": "1600",
    "Bugünkü Pist": "Çim",
    "Şehir": "İstanbul",
    "Son Hipodrom": "İstanbul"
  },
  {
    "Koşu": "3",
    "At İsmi": "BABA ZAMAN",
    "Profil Linki": "/at/89097/baba-zaman",
    "Jokey": "M.Kaya",
    "Son Kilo": "57",
    "Son Mesafe": "1200",
    "Son Pist": "Sentetik",
    "Son Derece": "1.20.57",
    "Kilo": "56",
    "Bugünkü Mesafe": "1600",
    "Bugünkü Pist": "Çim",
    "Şehir": "İstanbul",
    "Son Hipodrom": "İstanbul"
  },
  {
    "Koşu": "3",
    "At İsmi": "BAŞ AKTÖR",
    "Profil Linki": "/at/94690/bas-aktor",
    "Jokey": "Y.Gökçe",
    "Son Kilo": "50",
    "Son Mesafe": "1400",
    "Son Pist": "Çim",
    "Son Derece": "1.33.83",
    "Kilo": "56.2",
    "Bugünkü Mesafe": "1600",
    "Bugünkü Pist": "Çim",
    "Şehir": "İstanbul",
    "Son Hipodrom": "Bursa"
  },
  {
    "Koşu": "4",
    "At İsmi": "SAİTAMA",
    "Profil Linki": "/at/102979/saitama",
    "Jokey": "E.Aktuğ",
    "Son Kilo": "57",
    "Son Mesafe": "1400",
    "Son Pist": "Sentetik",
    "Son Derece": "1.26.25",
    "Kilo": "57",
    "Bugünkü Mesafe": "1600",
    "Bugünkü Pist": "Çim",
    "Şehir": "İstanbul",
    "Son Hipodrom": "İstanbul"
  },
  {
    "Koşu": "4",
    "At İsmi": "LINARES",
    "Profil Linki": "/at/103586/linares",
    "Jokey": "A.Yıldız",
    "Son Kilo": "55",
    "Son Mesafe": "1400",
    "Son Pist": "Çim",
    "Son Derece": "1.24.70",
    "Kilo": "57",
    "Bugünkü Mesafe": "1600",
    "Bugünkü Pist": "Çim",
    "Şehir": "İstanbul",
    "Son Hipodrom": "İstanbul"
  },
  {
    "Koşu": "4",
    "At İsmi": "AIMUS LIBERATUS",
    "Profil Linki": "/at/103045/aimus-liberatus",
    "Jokey": "E.Çankaya",
    "Son Kilo": "54",
    "Son Mesafe": "1600",
    "Son Pist": "Çim",
    "Son Derece": "1.38.27",
    "Kilo": "59",
    "Bugünkü Mesafe": "1600",
    "Bugünkü Pist": "Çim",
    "Şehir": "İstanbul",
    "Son Hipodrom": "İstanbul"
  },
  {
    "Koşu": "4",
    "At İsmi": "BALLAD KING",
    "Profil Linki": "/at/103762/ballad-king",
    "Jokey": "A.Sözen",
    "Son Kilo": "53",
    "Son Mesafe": "1300",
    "Son Pist": "Çim",
    "Son Derece": "1.18.96",
    "Kilo": "57",
    "Bugünkü Mesafe": "1600",
    "Bugünkü Pist": "Çim",
    "Şehir": "İstanbul",
    "Son Hipodrom": "İstanbul"
  },
  {
    "Koşu": "4",
    "At İsmi": "ERSELE BEYİ",
    "Profil Linki": "/at/103479/ersele-beyi",
    "Jokey": "M.Akyavuz",
    "Son Kilo": "54",
    "Son Mesafe": "1200",
    "Son Pist": "Kum",
    "Son Derece": "1.16.58",
    "Kilo": "57",
    "Bugünkü Mesafe": "1600",
    "Bugünkü Pist": "Çim",
    "Şehir": "İstanbul",
    "Son Hipodrom": "Ankara"
  },
  {
    "Koşu": "4",
    "At İsmi": "FALCONNIDAE",
    "Profil Linki": "/at/103453/falconnidae",
    "Jokey": "Gökh.Gökçe",
    "Son Kilo": "53",
    "Son Mesafe": "1300",
    "Son Pist": "Sentetik",
    "Son Derece": "1.20.79",
    "Kilo": "57",
    "Bugünkü Mesafe": "1600",
    "Bugünkü Pist": "Çim",
    "Şehir": "İstanbul",
    "Son Hipodrom": "İstanbul"
  },
  {
    "Koşu": "4",
    "At İsmi": "LORD OF DRAGON",
    "Profil Linki": "/at/103187/lord-of-dragon",
    "Jokey": "S.Tırpan",
    "Son Kilo": "53",
    "Son Mesafe": "1500",
    "Son Pist": "Çim",
    "Son Derece": "1.31.42",
    "Kilo": "57",
    "Bugünkü Mesafe": "1600",
    "Bugünkü Pist": "Çim",
    "Şehir": "İstanbul",
    "Son Hipodrom": "Bursa"
  },
  {
    "Koşu": "4",
    "At İsmi": "NOBLE STRENGTH",
    "Profil Linki": "/at/102498/noble-strength",
    "Jokey": "V.Abiş",
    "Son Kilo": "53",
    "Son Mesafe": "1600",
    "Son Pist": "Çim",
    "Son Derece": "1.37.60",
    "Kilo": "57",
    "Bugünkü Mesafe": "1600",
    "Bugünkü Pist": "Çim",
    "Şehir": "İstanbul",
    "Son Hipodrom": "İstanbul"
  },
  {
    "Koşu": "4",
    "At İsmi": "RUZYM",
    "Profil Linki": "/at/103272/ruzym",
    "Jokey": "B.M.Mırık",
    "Son Kilo": "52",
    "Son Mesafe": "1400",
    "Son Pist": "Sentetik",
    "Son Derece": "1.25.99",
    "Kilo": "55",
    "Bugünkü Mesafe": "1600",
    "Bugünkü Pist": "Çim",
    "Şehir": "İstanbul",
    "Son Hipodrom": "İstanbul"
  },
  {
    "Koşu": "5",
    "At İsmi": "AYSERA KIZ",
    "Profil Linki": "/at/102260/aysera-kiz",
    "Jokey": "M.Akyavuz",
    "Son Kilo": "59",
    "Son Mesafe": "1400",
    "Son Pist": "Çim",
    "Son Derece": "1.33.22",
    "Kilo": "57.1",
    "Bugünkü Mesafe": "1300",
    "Bugünkü Pist": "Çim",
    "Şehir": "İstanbul",
    "Son Hipodrom": "İstanbul"
  },
  {
    "Koşu": "5",
    "At İsmi": "SEMRAKAYA",
    "Profil Linki": "/at/102013/semrakaya",
    "Jokey": "S.Kaya",
    "Son Kilo": "59",
    "Son Mesafe": "1400",
    "Son Pist": "Çim",
    "Son Derece": "1.33.35",
    "Kilo": "55",
    "Bugünkü Mesafe": "1300",
    "Bugünkü Pist": "Çim",
    "Şehir": "İstanbul",
    "Son Hipodrom": "Bursa"
  },
  {
    "Koşu": "5",
    "At İsmi": "FISTIK ÇAMI",
    "Profil Linki": "/at/101389/fistik-cami",
    "Jokey": "A.Yıldız",
    "Son Kilo": "57",
    "Son Mesafe": "1400",
    "Son Pist": "Çim",
    "Son Derece": "1.33.84",
    "Kilo": "57",
    "Bugünkü Mesafe": "1300",
    "Bugünkü Pist": "Çim",
    "Şehir": "İstanbul",
    "Son Hipodrom": "İstanbul"
  },
  {
    "Koşu": "5",
    "At İsmi": "MİSS KÜBRA",
    "Profil Linki": "/at/102344/miss-kubra",
    "Jokey": "A.Sözen",
    "Son Kilo": "57",
    "Son Mesafe": "1300",
    "Son Pist": "Çim",
    "Son Derece": "1.26.38",
    "Kilo": "56",
    "Bugünkü Mesafe": "1300",
    "Bugünkü Pist": "Çim",
    "Şehir": "İstanbul",
    "Son Hipodrom": "Bursa"
  },
  {
    "Koşu": "5",
    "At İsmi": "CABİRE SULTAN",
    "Profil Linki": "/at/101787/cabire-sultan",
    "Jokey": "M.Kaya",
    "Son Kilo": "55",
    "Son Mesafe": "1300",
    "Son Pist": "Çim",
    "Son Derece": "1.29.80",
    "Kilo": "59",
    "Bugünkü Mesafe": "1300",
    "Bugünkü Pist": "Çim",
    "Şehir": "İstanbul",
    "Son Hipodrom": "Bursa"
  },
  {
    "Koşu": "5",
    "At İsmi": "EFSANE HANIM",
    "Profil Linki": "/at/101485/efsane-hanim",
    "Jokey": "G.Özçelik",
    "Son Kilo": "55",
    "Son Mesafe": "1300",
    "Son Pist": "Çim",
    "Son Derece": "1.26.85",
    "Kilo": "60",
    "Bugünkü Mesafe": "1300",
    "Bugünkü Pist": "Çim",
    "Şehir": "İstanbul",
    "Son Hipodrom": "Bursa"
  },
  {
    "Koşu": "5",
    "At İsmi": "DEVAŞA",
    "Profil Linki": "/at/101892/devasa",
    "Jokey": "V.Abiş",
    "Son Kilo": "54",
    "Son Mesafe": "1400",
    "Son Pist": "Çim",
    "Son Derece": "1.33.70",
    "Kilo": "57",
    "Bugünkü Mesafe": "1300",
    "Bugünkü Pist": "Çim",
    "Şehir": "İstanbul",
    "Son Hipodrom": "İstanbul"
  },
  {
    "Koşu": "5",
    "At İsmi": "KOPUK UÇURTMA",
    "Profil Linki": "/at/102184/kopuk-ucurtma",
    "Jokey": "Ö.Yıldırım",
    "Son Kilo": "54",
    "Son Mesafe": "1400",
    "Son Pist": "Çim",
    "Son Derece": "1.33.68",
    "Kilo": "57",
    "Bugünkü Mesafe": "1300",
    "Bugünkü Pist": "Çim",
    "Şehir": "İstanbul",
    "Son Hipodrom": "İstanbul"
  },
  {
    "Koşu": "5",
    "At İsmi": "TEKİNHANIM",
    "Profil Linki": "/at/101257/tekinhanim",
    "Jokey": "Murat Keçeci",
    "Son Kilo": "54",
    "Son Mesafe": "1400",
    "Son Pist": "Sentetik",
    "Son Derece": "1.35.29",
    "Kilo": "52.3",
    "Bugünkü Mesafe": "1300",
    "Bugünkü Pist": "Çim",
    "Şehir": "İstanbul",
    "Son Hipodrom": "İstanbul"
  },
  {
    "Koşu": "6",
    "At İsmi": "ESTIMATE",
    "Profil Linki": "/at/92147/estimate",
    "Jokey": "G.Kocakaya",
    "Son Kilo": "60",
    "Son Mesafe": "1900",
    "Son Pist": "Çim",
    "Son Derece": "1.57.20",
    "Kilo": "59",
    "Bugünkü Mesafe": "2100",
    "Bugünkü Pist": "Çim",
    "Şehir": "İstanbul",
    "Son Hipodrom": "Ankara"
  },
  {
    "Koşu": "6",
    "At İsmi": "ETSUKO",
    "Profil Linki": "/at/95285/etsuko",
    "Jokey": "Müs.Çelik",
    "Son Kilo": "60",
    "Son Mesafe": "2400",
    "Son Pist": "Çim",
    "Son Derece": "2.38.05",
    "Kilo": "58",
    "Bugünkü Mesafe": "2100",
    "Bugünkü Pist": "Çim",
    "Şehir": "İstanbul",
    "Son Hipodrom": "İstanbul"
  },
  {
    "Koşu": "6",
    "At İsmi": "MOONLIGHT FAIRY",
    "Profil Linki": "/at/90783/moonlight-fairy",
    "Jokey": "H.Karataş",
    "Son Kilo": "60",
    "Son Mesafe": "1900",
    "Son Pist": "Çim",
    "Son Derece": "1.57.20",
    "Kilo": "60",
    "Bugünkü Mesafe": "2100",
    "Bugünkü Pist": "Çim",
    "Şehir": "İstanbul",
    "Son Hipodrom": "İstanbul"
  },
  {
    "Koşu": "6",
    "At İsmi": "NYMPHADORA TONKS",
    "Profil Linki": "/at/95148/nymphadora-tonks",
    "Jokey": "M.Kaya",
    "Son Kilo": "60",
    "Son Mesafe": "1600",
    "Son Pist": "Çim",
    "Son Derece": "1.40.16",
    "Kilo": "60",
    "Bugünkü Mesafe": "2100",
    "Bugünkü Pist": "Çim",
    "Şehir": "İstanbul",
    "Son Hipodrom": "İstanbul"
  },
  {
    "Koşu": "6",
    "At İsmi": "OHRID INCISI",
    "Profil Linki": "/at/95838/ohrid-incisi",
    "Jokey": "M.Akyavuz",
    "Son Kilo": "60",
    "Son Mesafe": "1400",
    "Son Pist": "Çim",
    "Son Derece": "1.24.50",
    "Kilo": "54",
    "Bugünkü Mesafe": "2100",
    "Bugünkü Pist": "Çim",
    "Şehir": "İstanbul",
    "Son Hipodrom": "Ankara"
  },
  {
    "Koşu": "6",
    "At İsmi": "ROSSO E BIANCO",
    "Profil Linki": "/at/94301/rosso-e-bianco",
    "Jokey": "A.Yıldız",
    "Son Kilo": "60",
    "Son Mesafe": "1900",
    "Son Pist": "Çim",
    "Son Derece": "1.57.02",
    "Kilo": "58",
    "Bugünkü Mesafe": "2100",
    "Bugünkü Pist": "Çim",
    "Şehir": "İstanbul",
    "Son Hipodrom": "İstanbul"
  },
  {
    "Koşu": "6",
    "At İsmi": "SECRET IMAGE",
    "Profil Linki": "/at/95518/secret-image",
    "Jokey": "V.Abiş",
    "Son Kilo": "60",
    "Son Mesafe": "1900",
    "Son Pist": "Çim",
    "Son Derece": "1.56.93",
    "Kilo": "56",
    "Bugünkü Mesafe": "2100",
    "Bugünkü Pist": "Çim",
    "Şehir": "İstanbul",
    "Son Hipodrom": "İstanbul"
  },
  {
    "Koşu": "6",
    "At İsmi": "SHIROKE",
    "Profil Linki": "/at/95223/shiroke",
    "Jokey": "E.Çankaya",
    "Son Kilo": "60",
    "Son Mesafe": "1400",
    "Son Pist": "Çim",
    "Son Derece": "1.23.00",
    "Kilo": "55.2",
    "Bugünkü Mesafe": "2100",
    "Bugünkü Pist": "Çim",
    "Şehir": "İstanbul",
    "Son Hipodrom": "Ankara"
  },
  {
    "Koşu": "6",
    "At İsmi": "SPLENDID",
    "Profil Linki": "/at/88332/splendid",
    "Jokey": "A.Kurşun",
    "Son Kilo": "60",
    "Son Mesafe": "1900",
    "Son Pist": "Çim",
    "Son Derece": "1.57.80",
    "Kilo": "58",
    "Bugünkü Mesafe": "2100",
    "Bugünkü Pist": "Çim",
    "Şehir": "İstanbul",
    "Son Hipodrom": "İstanbul"
  },
  {
    "Koşu": "6",
    "At İsmi": "STASERA",
    "Profil Linki": "/at/95779/stasera",
    "Jokey": "A.Sözen",
    "Son Kilo": "60",
    "Son Mesafe": "1400",
    "Son Pist": "Sentetik",
    "Son Derece": "1.24.62",
    "Kilo": "55",
    "Bugünkü Mesafe": "2100",
    "Bugünkü Pist": "Çim",
    "Şehir": "İstanbul",
    "Son Hipodrom": "İstanbul"
  },
  {
    "Koşu": "6",
    "At İsmi": "BEAUTY OF DARKNESS",
    "Profil Linki": "/at/99693/beauty-of-darkness",
    "Jokey": "Ö.Yıldırım",
    "Son Kilo": "56.5",
    "Son Mesafe": "2400",
    "Son Pist": "Çim",
    "Son Derece": "2.29.91",
    "Kilo": "54.3",
    "Bugünkü Mesafe": "2100",
    "Bugünkü Pist": "Çim",
    "Şehir": "İstanbul",
    "Son Hipodrom": "İstanbul"
  },
  {
    "Koşu": "7",
    "At İsmi": "CATCH THE STARS",
    "Profil Linki": "/at/92171/catch-the-stars",
    "Jokey": "Ahmet Çelik",
    "Son Kilo": "63",
    "Son Mesafe": "2200",
    "Son Pist": "Sentetik",
    "Son Derece": "2.21.59",
    "Kilo": "63",
    "Bugünkü Mesafe": "2100",
    "Bugünkü Pist": "Çim",
    "Şehir": "İstanbul",
    "Son Hipodrom": "İstanbul"
  },
  {
    "Koşu": "7",
    "At İsmi": "LAUREATE",
    "Profil Linki": "/at/98128/laureate",
    "Jokey": "G.Kocakaya",
    "Son Kilo": "58",
    "Son Mesafe": "1400",
    "Son Pist": "Çim",
    "Son Derece": "1.24.49",
    "Kilo": "58.5",
    "Bugünkü Mesafe": "2100",
    "Bugünkü Pist": "Çim",
    "Şehir": "İstanbul",
    "Son Hipodrom": "İstanbul"
  },
  {
    "Koşu": "7",
    "At İsmi": "MISTER PROTEO",
    "Profil Linki": "/at/93476/mister-proteo",
    "Jokey": "A.Kurşun",
    "Son Kilo": "60.5",
    "Son Mesafe": "1900",
    "Son Pist": "Çim",
    "Son Derece": "1.56.55",
    "Kilo": "62",
    "Bugünkü Mesafe": "2100",
    "Bugünkü Pist": "Çim",
    "Şehir": "İstanbul",
    "Son Hipodrom": "İstanbul"
  },
  {
    "Koşu": "7",
    "At İsmi": "UMUTBEY",
    "Profil Linki": "/at/89902/umutbey",
    "Jokey": "E.Çankaya",
    "Son Kilo": "60.5",
    "Son Mesafe": "2100",
    "Son Pist": "Çim",
    "Son Derece": "2.12.70",
    "Kilo": "60",
    "Bugünkü Mesafe": "2100",
    "Bugünkü Pist": "Çim",
    "Şehir": "İstanbul",
    "Son Hipodrom": "İstanbul"
  },
  {
    "Koşu": "7",
    "At İsmi": "YILDIRIMDURALİ",
    "Profil Linki": "/at/96731/yildirimdurali",
    "Jokey": "M.M.Bilgin",
    "Son Kilo": "57.5",
    "Son Mesafe": "1600",
    "Son Pist": "Çim",
    "Son Derece": "1.38.29",
    "Kilo": "56.3",
    "Bugünkü Mesafe": "2100",
    "Bugünkü Pist": "Çim",
    "Şehir": "İstanbul",
    "Son Hipodrom": "İstanbul"
  },
  {
    "Koşu": "7",
    "At İsmi": "LAST MOMENT",
    "Profil Linki": "/at/100668/last-moment",
    "Jokey": "A.Aslan",
    "Son Kilo": "50",
    "Son Mesafe": "1900",
    "Son Pist": "Çim",
    "Son Derece": "1.56.31",
    "Kilo": "52.5",
    "Bugünkü Mesafe": "2100",
    "Bugünkü Pist": "Çim",
    "Şehir": "İstanbul",
    "Son Hipodrom": "İstanbul"
  },
  {
    "Koşu": "7",
    "At İsmi": "ACAR TAY",
    "Profil Linki": "/at/91164/acar-tay",
    "Jokey": "Hakan Yıldız",
    "Son Kilo": "50",
    "Son Mesafe": "1900",
    "Son Pist": "Çim",
    "Son Derece": "1.57.65",
    "Kilo": "57",
    "Bugünkü Mesafe": "2100",
    "Bugünkü Pist": "Çim",
    "Şehir": "İstanbul",
    "Son Hipodrom": "İstanbul"
  },
  {
    "Koşu": "8",
    "At İsmi": "MAGIC WEAPON",
    "Profil Linki": "/at/99801/magic-weapon",
    "Jokey": "A.Kurşun",
    "Son Kilo": "61",
    "Son Mesafe": "1600",
    "Son Pist": "Çim",
    "Son Derece": "1.36.70",
    "Kilo": "58",
    "Bugünkü Mesafe": "1500",
    "Bugünkü Pist": "Sentetik",
    "Şehir": "İstanbul",
    "Son Hipodrom": "İstanbul"
  },
  {
    "Koşu": "8",
    "At İsmi": "BANDOLERO",
    "Profil Linki": "/at/99580/bandolero",
    "Jokey": "E.Çankaya",
    "Son Kilo": "58",
    "Son Mesafe": "2100",
    "Son Pist": "Sentetik",
    "Son Derece": "2.11.05",
    "Kilo": "57.5",
    "Bugünkü Mesafe": "1500",
    "Bugünkü Pist": "Sentetik",
    "Şehir": "İstanbul",
    "Son Hipodrom": "İstanbul"
  },
  {
    "Koşu": "8",
    "At İsmi": "FATHER MEHMET",
    "Profil Linki": "/at/98362/father-mehmet",
    "Jokey": "A.Yıldız",
    "Son Kilo": "58",
    "Son Mesafe": "1400",
    "Son Pist": "Kum",
    "Son Derece": "1.26.14",
    "Kilo": "61",
    "Bugünkü Mesafe": "1500",
    "Bugünkü Pist": "Sentetik",
    "Şehir": "İstanbul",
    "Son Hipodrom": "Kocaeli"
  },
  {
    "Koşu": "8",
    "At İsmi": "FIREBENDER",
    "Profil Linki": "/at/98323/firebender",
    "Jokey": "V.Abiş",
    "Son Kilo": "58",
    "Son Mesafe": "2100",
    "Son Pist": "Çim",
    "Son Derece": "2.12.22",
    "Kilo": "59.5",
    "Bugünkü Mesafe": "1500",
    "Bugünkü Pist": "Sentetik",
    "Şehir": "İstanbul",
    "Son Hipodrom": "İstanbul"
  },
  {
    "Koşu": "8",
    "At İsmi": "QUANTUM OF SOLACE",
    "Profil Linki": "/at/98627/quantum-of-solace",
    "Jokey": "Ö.Yıldırım",
    "Son Kilo": "58",
    "Son Mesafe": "1900",
    "Son Pist": "Kum",
    "Son Derece": "2.06.38",
    "Kilo": "60",
    "Bugünkü Mesafe": "1500",
    "Bugünkü Pist": "Sentetik",
    "Şehir": "İstanbul",
    "Son Hipodrom": "Bursa"
  },
  {
    "Koşu": "8",
    "At İsmi": "LİVZARA",
    "Profil Linki": "/at/98115/livzara",
    "Jokey": "K.Tokaçoğlu",
    "Son Kilo": "56",
    "Son Mesafe": "1300",
    "Son Pist": "Kum",
    "Son Derece": "1.22.12",
    "Kilo": "57.5",
    "Bugünkü Mesafe": "1500",
    "Bugünkü Pist": "Sentetik",
    "Şehir": "İstanbul",
    "Son Hipodrom": "Ankara"
  },
  {
    "Koşu": "9",
    "At İsmi": "RAIN BEAUTY",
    "Profil Linki": "/at/103350/rain-beauty",
    "Jokey": "Müs.Çelik",
    "Son Kilo": "59",
    "Son Mesafe": "1300",
    "Son Pist": "Sentetik",
    "Son Derece": "1.20.13",
    "Kilo": "55",
    "Bugünkü Mesafe": "1300",
    "Bugünkü Pist": "Sentetik",
    "Şehir": "İstanbul",
    "Son Hipodrom": "İstanbul"
  },
  {
    "Koşu": "9",
    "At İsmi": "AMBER TREASURE",
    "Profil Linki": "/at/103640/amber-treasure",
    "Jokey": "M.Kaya",
    "Son Kilo": "57",
    "Son Mesafe": "1200",
    "Son Pist": "Çim",
    "Son Derece": "1.16.94",
    "Kilo": "57",
    "Bugünkü Mesafe": "1300",
    "Bugünkü Pist": "Sentetik",
    "Şehir": "İstanbul",
    "Son Hipodrom": "İstanbul"
  },
  {
    "Koşu": "9",
    "At İsmi": "BIMINI ROAD",
    "Profil Linki": "/at/103617/bimini-road",
    "Jokey": "İ.Koyuncu",
    "Son Kilo": "57",
    "Son Mesafe": "1400",
    "Son Pist": "Çim",
    "Son Derece": "1.27.83",
    "Kilo": "57",
    "Bugünkü Mesafe": "1300",
    "Bugünkü Pist": "Sentetik",
    "Şehir": "İstanbul",
    "Son Hipodrom": "İstanbul"
  },
  {
    "Koşu": "9",
    "At İsmi": "ELISA DAY",
    "Profil Linki": "/at/102891/elisa-day",
    "Jokey": "A.Kurşun",
    "Son Kilo": "57",
    "Son Mesafe": "1100",
    "Son Pist": "Çim",
    "Son Derece": "1.08.56",
    "Kilo": "57",
    "Bugünkü Mesafe": "1300",
    "Bugünkü Pist": "Sentetik",
    "Şehir": "İstanbul",
    "Son Hipodrom": "İstanbul"
  },
  {
    "Koşu": "9",
    "At İsmi": "FINALLY IDYLL",
    "Profil Linki": "/at/104242/finally-idyll",
    "Jokey": "Murat Keçeci",
    "Son Kilo": "54",
    "Son Mesafe": "1200",
    "Son Pist": "Sentetik",
    "Son Derece": "1.16.19",
    "Kilo": "57",
    "Bugünkü Mesafe": "1300",
    "Bugünkü Pist": "Sentetik",
    "Şehir": "İstanbul",
    "Son Hipodrom": "İstanbul"
  },
  {
    "Koşu": "9",
    "At İsmi": "HILDA",
    "Profil Linki": "/at/103866/hilda",
    "Jokey": "A.Yıldız",
    "Son Kilo": "57",
    "Son Mesafe": "1400",
    "Son Pist": "Çim",
    "Son Derece": "1.27.00",
    "Kilo": "57",
    "Bugünkü Mesafe": "1300",
    "Bugünkü Pist": "Sentetik",
    "Şehir": "İstanbul",
    "Son Hipodrom": "İstanbul"
  },
  {
    "Koşu": "9",
    "At İsmi": "LADAMADELAMAFIA",
    "Profil Linki": "/at/103854/ladamadelamafia",
    "Jokey": "A.Sözen",
    "Son Kilo": "57",
    "Son Mesafe": "1400",
    "Son Pist": "Kum",
    "Son Derece": "1.31.74",
    "Kilo": "57.7",
    "Bugünkü Mesafe": "1300",
    "Bugünkü Pist": "Sentetik",
    "Şehir": "İstanbul",
    "Son Hipodrom": "Bursa"
  },
  {
    "Koşu": "9",
    "At İsmi": "MUSTANG SALLY",
    "Profil Linki": "/at/104460/mustang-sally",
    "Jokey": "A.Aslan",
    "Son Kilo": "57",
    "Son Mesafe": "1200",
    "Son Pist": "Çim",
    "Son Derece": "1.16.19",
    "Kilo": "55",
    "Bugünkü Mesafe": "1300",
    "Bugünkü Pist": "Sentetik",
    "Şehir": "İstanbul",
    "Son Hipodrom": "İstanbul"
  },
  {
    "Koşu": "9",
    "At İsmi": "SMOOTH CRIMINAL",
    "Profil Linki": "/at/103865/smooth-criminal",
    "Jokey": "G.Özçelik",
    "Son Kilo": "57",
    "Son Mesafe": "1200",
    "Son Pist": "Sentetik",
    "Son Derece": "1.15.86",
    "Kilo": "57",
    "Bugünkü Mesafe": "1300",
    "Bugünkü Pist": "Sentetik",
    "Şehir": "İstanbul",
    "Son Hipodrom": "İstanbul"
  },
  {
    "Koşu": "9",
    "At İsmi": "ULTIMATE POWER",
    "Profil Linki": "/at/103712/ultimate-power",
    "Jokey": "E.Aktuğ",
    "Son Kilo": "57",
    "Son Mesafe": "1200",
    "Son Pist": "Çim",
    "Son Derece": "1.14.88",
    "Kilo": "55",
    "Bugünkü Mesafe": "1300",
    "Bugünkü Pist": "Sentetik",
    "Şehir": "İstanbul",
    "Son Hipodrom": "İstanbul"
  },
  {
    "Koşu": "9",
    "At İsmi": "VEN CONMİGO",
    "Profil Linki": "/at/102488/ven-conmigo",
    "Jokey": "Y.Gökçe",
    "Son Kilo": "53",
    "Son Mesafe": "1200",
    "Son Pist": "Sentetik",
    "Son Derece": "1.14.33",
    "Kilo": "52.5",
    "Bugünkü Mesafe": "1300",
    "Bugünkü Pist": "Sentetik",
    "Şehir": "İstanbul",
    "Son Hipodrom": "İstanbul"
  }
]